hai/__init__.py
hai/version.py
hai/apis/__init__.py
hai/apis/openai_api.py
hai/apis/basic/__init__.py
hai/apis/basic/argparse.py
hai/apis/basic/base.py
hai/apis/basic/grpc.py
hai/apis/basic/registry.py
hai/apis/basic/utils.py
hai/apis/hub/__init__.py
hai/apis/hub/hubs.py
hai/apis/modules/__init__.py
hai/apis/modules/ResNet/ResNet.py
hai/apis/modules/ResNet/__init__.py
hai/apis/modules/UNet/__init__.py
hai/apis/modules/UNet/argparse_config.py
hai/apis/modules/UNet/evaluate_api.py
hai/apis/modules/UNet/predict_api.py
hai/apis/modules/UNet/train_api.py
hai/apis/modules/UNet/unet_api.py
hai/apis/modules/YOLOv5/__init__.py
hai/apis/workers_api/__init__.py
hai/apis/workers_api/model.py
hai/apis/workers_api/llm/__init__.py
hai/apis/workers_api/llm/llm.py
hai/apis/workers_api/llm/tokenizer.py
hai/apis/workers_api/nougat/__init__.py
hai/apis/workers_api/nougat/pdf_process.py
hai/apis/workers_api/sam/__init__.py
hai/apis/workers_api/sam/pre_process.py
hai/apis/workers_api/sam/seg_via_sam.py
hai/configs/CONST.py
hai/configs/__init__.py
hai/configs/uaii_deepsort_config.py
hai/configs/uaii_seyolov5_config.py
hai/configs/uaii_stream_config.py
hai/configs/visible_loader_config.py
hai/configs/Base/__init__.py
hai/configs/Base/hai_config.py
hai/configs/urls/datasets.json
hai/configs/urls/hub_models.json
hai/modules/__init__.py
hai/modules/model_hub.py
hai/modules/detection/__init__.py
hai/modules/exporter/__init__.py
hai/modules/exporter/images_exporter/__init__.py
hai/modules/loader/__init__.py
hai/modules/loader/images_loader/__init__.py
hai/modules/loader/images_loader/dataloader.py
hai/modules/loader/images_loader/dataset_torch.py
hai/modules/loader/images_loader/datasets.py
hai/modules/segmentation/__init__.py
hai/modules/segmentation/Pytorch_UNet/__init__.py
hai/modules/segmentation/Pytorch_UNet/evaluate.py
hai/modules/segmentation/Pytorch_UNet/hubconf.py
hai/modules/segmentation/Pytorch_UNet/predict.py
hai/modules/segmentation/Pytorch_UNet/train.py
hepai-1.3.4.dist-info/METADATA
hepai-1.3.4.dist-info/WHEEL
hepai-1.3.4.dist-info/entry_points.txt
hepai-1.3.4.dist-info/top_level.txt
hepai-1.3.4.dist-info/RECORD
