Metadata-Version: 2.4
Name: hepai
Version: 1.3.4
Summary: High energy physics Artificial Intelligence platform, HAI.
Home-page: https://github.com/hepaihub/hepai
Author: Zhengde Zhang, Dongbo Xiong
Author-email: zdzhang@ihep.ac.cn; xiongdb@ihep.ac.cn
License: MIT
Classifier: License :: OSI Approved :: MIT License
Classifier: Programming Language :: Python
Classifier: Programming Language :: Python :: 3
Classifier: Programming Language :: Python :: 3.8
Classifier: Programming Language :: Python :: 3.9
Classifier: Programming Language :: Python :: 3.10
Classifier: Programming Language :: Python :: 3.11
Classifier: Programming Language :: Python :: 3.12
Classifier: Programming Language :: Python :: Implementation :: CPython
Classifier: Programming Language :: Python :: Implementation :: PyPy
Requires-Python: >=3.10.0
Requires-Dist: pyyaml
Requires-Dist: easydict
Requires-Dist: fastapi
Requires-Dist: requests
Requires-Dist: uvicorn
Requires-Dist: openai>=1.63.0
Requires-Dist: anthropic>=0.59.0
Requires-Dist: python-dotenv>=1.1.1
Requires-Dist: damei>=1.1.135
Requires-Dist: mcp>=1.15.0
Requires-Dist: numpy
Provides-Extra: full
Requires-Dist: pyyaml; extra == "full"
Requires-Dist: easydict; extra == "full"
Requires-Dist: fastapi; extra == "full"
Requires-Dist: requests; extra == "full"
Requires-Dist: uvicorn; extra == "full"
Requires-Dist: openai>=1.63.0; extra == "full"
Requires-Dist: python-dotenv>=1.1.1; extra == "full"
Requires-Dist: numpy; extra == "full"
Requires-Dist: pillow; extra == "full"
Requires-Dist: opencv-python; extra == "full"
Requires-Dist: autogen-agentchat>=0.5.5; extra == "full"
Requires-Dist: autogen-core>=0.5.5; extra == "full"
Requires-Dist: autogen-ext>=0.5.5; extra == "full"
Requires-Dist: schedule>=1.2.2; extra == "full"
Requires-Dist: tiktoken>=0.9.0; extra == "full"
Requires-Dist: passlib>=1.7.4; extra == "full"
Requires-Dist: jwt>=1.3.1; extra == "full"
Requires-Dist: aiohttp>=3.11.11; extra == "full"
Requires-Dist: mcp>=1.15.0; extra == "full"
Requires-Dist: python-multipart>=0.0.18; extra == "full"
Requires-Dist: json_schema_to_pydantic>=0.2.4; extra == "full"
Requires-Dist: grpcio-tools; extra == "full"
Requires-Dist: damei; extra == "full"
Requires-Dist: tqdm; extra == "full"
Requires-Dist: wandb; extra == "full"
Requires-Dist: pydantic>=2.11.3; extra == "full"
Requires-Dist: python-dateutil; extra == "full"
Requires-Dist: httpx>=0.28.1; extra == "full"
Requires-Dist: markdown; extra == "full"
Dynamic: author
Dynamic: author-email
Dynamic: classifier
Dynamic: description
Dynamic: description-content-type
Dynamic: home-page
Dynamic: license
Dynamic: provides-extra
Dynamic: requires-dist
Dynamic: requires-python
Dynamic: summary
